<?xml version='1.0' encoding='utf-8'?>
<compendium><spell><name text="Commune" /><classes text="Paladin (Glory)" /></spell><spell><name text="Compulsion" /><classes text="Paladin (Glory)" /></spell><spell><name text="Enhance Ability" /><classes text="Paladin (Glory)" /></spell><spell><name text="Flame Strike" /><classes text="Paladin (Glory)" /></spell><spell><name text="Freedom of Movement" /><classes text="Paladin (Glory)" /></spell><spell><name text="Guiding Bolt" /><classes text="Paladin (Glory)" /></spell><spell><name text="Haste" /><classes text="Paladin (Glory)" /></spell><spell><name text="Heroism" /><classes text="Paladin (Glory)" /></spell><spell><name text="Magic Weapon" /><classes text="Paladin (Glory)" /></spell><spell><name text="Protection from Energy" /><classes text="Paladin (Glory)" /></spell></compendium>